debuggpt/__init__.py
debuggpt/gpt_debug.py
debuggpt/options.py
debuggpt/record_stdout.py
debuggpt-0.1.1.dist-info/METADATA
debuggpt-0.1.1.dist-info/WHEEL
debuggpt-0.1.1.dist-info/RECORD
