Metadata-Version: 2.1
Name: debuggpt
Version: 0.1.1
Summary: The realest AI debugger in the game.
Author-email: Ryan Young <dev@ryayoung.com>
License-Expression: MIT
Classifier: Development Status :: 3 - Alpha
Classifier: Intended Audience :: Developers
Classifier: License :: OSI Approved :: MIT License
Classifier: Operating System :: OS Independent
Classifier: Programming Language :: Python :: 3.11
Classifier: Topic :: Software Development :: Libraries
Requires-Dist: openai
